pymultimonitor/__init__.py
pymultimonitor/cinterface/__init__.py
pymultimonitor/cinterface/constants/DisplayConfigDeviceInfo.py
pymultimonitor/cinterface/constants/DisplayConfigTopology.py
pymultimonitor/cinterface/constants/DisplayModeInfo.py
pymultimonitor/cinterface/constants/QueryDisplayConfigFlag.py
pymultimonitor/cinterface/constants/SetDisplayConfigFlag.py
pymultimonitor/cinterface/constants/__init__.py
pymultimonitor/cinterface/functions/__init__.py
pymultimonitor/cinterface/functions/winuser/Winuser.py
pymultimonitor/cinterface/functions/winuser/__init__.py
pymultimonitor/cinterface/structures/__init__.py
pymultimonitor/cinterface/structures/displaydevicesreference/__init__.py
pymultimonitor/cinterface/structures/displaydevicesreference/wingdi/DisplayConfigStructures.py
pymultimonitor/cinterface/structures/displaydevicesreference/wingdi/__init__.py
pymultimonitor/cinterface/structures/monitorconfiguration/__init__.py
pymultimonitor/cinterface/structures/monitorconfiguration/physicalmonitorenumerationapi/PhysicalMonitorStructures.py
pymultimonitor/cinterface/structures/monitorconfiguration/physicalmonitorenumerationapi/__init__.py
pymultimonitor/core/DisplayBrightness.py
pymultimonitor/core/DisplayInfo.py
pymultimonitor/core/DisplayMonitors.py
pymultimonitor/core/DisplayTopology.py
pymultimonitor/core/__init__.py
pymultimonitor/output/Brightness.py
pymultimonitor/output/PhysicalMonitor.py
pymultimonitor/output/__init__.py
pymultimonitor-0.2.0.dist-info/LICENSE
pymultimonitor-0.2.0.dist-info/WHEEL
pymultimonitor-0.2.0.dist-info/METADATA
pymultimonitor-0.2.0.dist-info/RECORD
