Metadata-Version: 2.1
Name: pymultimonitor
Version: 0.2.0
Summary: 
Home-page: https://github.com/Dibakarroy1997/pymultimonitor
Keywords: display,windows
Author: debakarr
Author-email: debakar.roy@intel.com
Requires-Python: >=3.8,<4.0
Classifier: Programming Language :: Python :: 3
Classifier: Programming Language :: Python :: 3.10
Classifier: Programming Language :: Python :: 3.8
Classifier: Programming Language :: Python :: 3.9
Project-URL: Repository, https://github.com/Dibakarroy1997/pymultimonitor
